{
  "id": 1760765988918,
  "fecha": "2025-10-18T05:39:48.918Z",
  "tipoServicio": "Vigilia",
  "fechaServicio": "2025-10-17",
  "horaInicio": "20:30",
  "horaFinalizacion": "00:40",
  "observacionesGenerales": "los microfonos inalambricos no tienen baterias",
  "nombreResponsable": "Margie Villarruel",
  "rolResponsable": "Servidor",
  "equipos": {
    "audio": {
      "microfonos-inalambricos": {
        "estado": "bueno",
        "observaciones": ""
      },
      "microfonos-alambricos": {
        "estado": "bueno",
        "observaciones": ""
      },
      "planta-sonido": {
        "estado": "bueno",
        "observaciones": ""
      }
    },
    "computadoras": {
      "cpu-principal": {
        "estado": "bueno",
        "observaciones": ""
      },
      "monitor-principal": {
        "estado": "bueno",
        "observaciones": ""
      }
    },
    "conectividad": {
      "cables-hdmi": {
        "estado": "bueno",
        "observaciones": ""
      },
      "cables-audio": {
        "estado": "bueno",
        "observaciones": ""
      }
    },
    "internet": {
      "router-wifi": {
        "estado": "bueno",
        "observaciones": ""
      }
    },
    "video": {
      "camara-celular": {
        "estado": "bueno",
        "observaciones": ""
      },
      "tv-1": {
        "estado": "bueno",
        "observaciones": ""
      },
      "tv-2": {
        "estado": "bueno",
        "observaciones": ""
      }
    }
  }
}