{
  "id": 1757255568937,
  "fecha": "2025-09-07T14:32:48.937Z",
  "tipoServicio": "Servicio Familiar Domingo AM",
  "fechaServicio": "2025-09-07",
  "horaInicio": "20:00",
  "horaFinalizacion": "",
  "observacionesGenerales": "",
  "nombreResponsable": "Miguel Orzxo",
  "rolResponsable": "Servidor",
  "equipos": {
    "audio": {
      "microfonos-inalambricos": {
        "estado": "regular",
        "observaciones": "2 MICROFONOS NO ESTÁN OPERATIVOS."
      },
      "microfonos-alambricos": {
        "estado": "regular",
        "observaciones": ""
      },
      "planta-sonido": {
        "estado": "bueno",
        "observaciones": ""
      }
    },
    "computadoras": {
      "cpu-principal": {
        "estado": "bueno",
        "observaciones": ""
      },
      "monitor-principal": {
        "estado": "bueno",
        "observaciones": ""
      }
    },
    "conectividad": {
      "cables-hdmi": {
        "estado": "bueno",
        "observaciones": ""
      },
      "cables-audio": {
        "estado": "bueno",
        "observaciones": ""
      }
    },
    "internet": {
      "router-wifi": {
        "estado": "bueno",
        "observaciones": ""
      }
    },
    "video": {
      "camara-celular": {
        "estado": "bueno",
        "observaciones": ""
      },
      "tv-1": {
        "estado": "bueno",
        "observaciones": ""
      },
      "tv-2": {
        "estado": "bueno",
        "observaciones": ""
      }
    }
  }
}